pigeon_transitions/__init__.py
pigeon_transitions/__main__.py
pigeon_transitions/base.py
pigeon_transitions/config.py
pigeon_transitions/exceptions.py
pigeon_transitions/machines.py
pigeon_transitions/root.py
pigeon_transitions-4.0.1.dist-info/licenses/LICENSE
pigeon_transitions-4.0.1.dist-info/METADATA
pigeon_transitions-4.0.1.dist-info/WHEEL
pigeon_transitions-4.0.1.dist-info/entry_points.txt
pigeon_transitions-4.0.1.dist-info/top_level.txt
pigeon_transitions-4.0.1.dist-info/RECORD
