Metadata-Version: 2.4
Name: pigeon-transitions
Version: 4.0.1
Summary: A state machine framework for Pigeon.
Author-email: Cameron Devine <cameron.devine@alleninstitute.org>
License: BSD 3 Clause
Project-URL: Homepage, https://github.com/AllenInstitute/pigeon-transitions
Project-URL: Repository, https://github.com/AllenInstitute/pigeon-transitions
Project-URL: Issues, https://github.com/AllenInstitute/pigeon-transitions/issues
Requires-Python: >=3.10
License-File: LICENSE
Requires-Dist: pigeon-client>=2.3.0
Requires-Dist: transitions==0.9.1
Requires-Dist: graphviz
Requires-Dist: pydantic
Requires-Dist: pyyaml
Provides-Extra: test
Requires-Dist: pytest; extra == "test"
Requires-Dist: pytest-mock; extra == "test"
Requires-Dist: pytest-timeout; extra == "test"
Dynamic: license-file
